apnapackage/__init__.py
apnapackage-0.1.dist-info/METADATA
apnapackage-0.1.dist-info/WHEEL
apnapackage-0.1.dist-info/top_level.txt
apnapackage-0.1.dist-info/RECORD
