Metadata-Version: 2.1
Name: apnapackage
Version: 0.1
Summary: this is very heavy or useful calculator
Home-page: UNKNOWN
Author: AFZAL GURU
Author-email: mdafzalkhan78610@gmail.com
License: UNKNOWN
Platform: UNKNOWN
Classifier: Programming Language :: Python :: 3
Classifier: License :: OSI Approved :: MIT License
Classifier: Operating System :: OS Independent
